{
  "projects": [
    {
      "name": "Business site",
      "image": "./Assets/businessSite.png",
      "tags": [
        "HTML5",
        " CSS3",
        " JavaScript"
      ],
      "description":"Dummy model agency website, built this to explore responsive design, interactivity and layout techniques. Site includes functional navigation bar, hamburger menu on smaller screens, interactive buttons that change theme, form with submission to httpbin.",
      "netlify": "https://willz-models.netlify.app/",
      "github": "https://github.com/Nicolinabl/Nicolina-business-site?tab=readme-ov-file"
    },
    {
      "name": "Weather app",
      "image": "",
      "tags": [
        "HTML5",
        " CSS3 ",
        " JavaScript",
        " TypeScript",
        " SMHI API"
      ],
      "description": "Functioning weather app collecting real time data using SMHI open API. Displaying real time temperature for Stockholm,  different messages and colors depending on weather.",
      "netlify": "https://weather-app-rock-3.netlify.app/",
      "github": "https://github.com/Nicolinabl/js-project-weather-app"
    },
    {
      "name": "Event Finder",
      "image": "",
      "tags": [
        "HTML5",
        " CSS3 ",
        " JavaScript",
        " TypeScript "
      ],
      "description": "Event finder page. Focus while building this site was accessibility, following WCAG AA standards.",
      "netlify": "https://eventacc.netlify.app/",
      "github": "https://github.com/qabalany/js-project-accessibility"
    },
    {
      "name": "Recipe Library",
      "image": "",
      "tags": [
        "HTML5",
        " CSS3",
        " JavaScript",
        " TypeScript",
        " APIs"
      ],
      "description":"Recipe app fetching recipes from spoonacular API. Options to display recipes according to chosen filters and sorting options. Taps into saved backup collection of recipes if daily quota of API is reached.  HTML, CSS, JavaScript, Spoonacular API.",
      "netlify": "https://nicolina-recipe-library.netlify.app/",
      "github": "https://github.com/Nicolinabl/js-project-recipe-library"
    }
  ]
}